dayu_widgets3/__init__.py
dayu_widgets3/__version__.py
dayu_widgets3/alert.py
dayu_widgets3/avatar.py
dayu_widgets3/badge.py
dayu_widgets3/breadcrumb.py
dayu_widgets3/browser.py
dayu_widgets3/button_group.py
dayu_widgets3/card.py
dayu_widgets3/carousel.py
dayu_widgets3/check_box.py
dayu_widgets3/collapse.py
dayu_widgets3/color_palette.py
dayu_widgets3/combo_box.py
dayu_widgets3/completer.py
dayu_widgets3/db_path_buttons.py
dayu_widgets3/divider.py
dayu_widgets3/dock_widget.py
dayu_widgets3/drawer.py
dayu_widgets3/field_mixin.py
dayu_widgets3/flow_layout.py
dayu_widgets3/form.py
dayu_widgets3/header_view.py
dayu_widgets3/item_model.py
dayu_widgets3/item_view.py
dayu_widgets3/item_view_full_set.py
dayu_widgets3/item_view_set.py
dayu_widgets3/label.py
dayu_widgets3/line_edit.py
dayu_widgets3/line_tab_widget.py
dayu_widgets3/loading.py
dayu_widgets3/menu.py
dayu_widgets3/menu_tab_widget.py
dayu_widgets3/message.py
dayu_widgets3/mixin.py
dayu_widgets3/page.py
dayu_widgets3/popup.py
dayu_widgets3/progress_bar.py
dayu_widgets3/progress_circle.py
dayu_widgets3/push_button.py
dayu_widgets3/qt/__init__.py
dayu_widgets3/radio_button.py
dayu_widgets3/slider.py
dayu_widgets3/spin_box.py
dayu_widgets3/splitter.py
dayu_widgets3/stacked_widget.py
dayu_widgets3/static/__init__.py
dayu_widgets3/static/add_line.svg
dayu_widgets3/static/alert_fill.svg
dayu_widgets3/static/alert_line.svg
dayu_widgets3/static/app-houdini.png
dayu_widgets3/static/app-maya.png
dayu_widgets3/static/app-nuke.png
dayu_widgets3/static/attachment_line.svg
dayu_widgets3/static/avatar.png
dayu_widgets3/static/base.json
dayu_widgets3/static/big_view.svg
dayu_widgets3/static/bold.svg
dayu_widgets3/static/calendar_fill.png
dayu_widgets3/static/calendar_fill.svg
dayu_widgets3/static/calendar_fill_dark.png
dayu_widgets3/static/calendar_fill_dark.svg
dayu_widgets3/static/calendar_line.png
dayu_widgets3/static/calendar_line.svg
dayu_widgets3/static/calendar_line_dark.png
dayu_widgets3/static/calendar_line_dark.svg
dayu_widgets3-0.2.0.dist-info/METADATA
dayu_widgets3-0.2.0.dist-info/WHEEL
dayu_widgets3-0.2.0.dist-info/RECORD
