Metadata-Version: 2.1
Name: dayu-widgets3
Version: 0.2.0
Summary: Components for PySide2/PySide6.
Home-page: https://github.com/muyr/dayu_widgets3
License: MIT
Keywords: UI,PySide2,PyQt5,PySide6
Author: muyanru
Author-email: muyanru@163.com
Requires-Python: >=3.7,<3.11
Classifier: License :: OSI Approved :: MIT License
Classifier: Programming Language :: Python :: 3
Classifier: Programming Language :: Python :: 3.7
Classifier: Programming Language :: Python :: 3.8
Classifier: Programming Language :: Python :: 3.9
Classifier: Programming Language :: Python :: 3.10
Requires-Dist: qtpy (>=2.3.1,<3.0.0)
Project-URL: Documentation, https://muyr.github.io/dayu_widgets3/#/
Project-URL: Repository, https://github.com/muyr/dayu_widgets3
